{
  "runID": "000074",
  "fitness": 2.7369575177311702,
  "generation": 9,
  "core": {
    "right": {
      "hinge": {
        "brick": {
          "front": {
            "hinge": {
              "brick": {
                "front": {
                  "hinge": {
                    "brick": {
                      "front": {},
                      "right": {},
                      "left": {},
                      "rotation": 1.5707963267948966
                    },
                    "rotation": 0.0
                  }
                },
                "right": {
                  "hinge": {
                    "brick": {
                      "front": {},
                      "right": {},
                      "left": {},
                      "rotation": 1.5707963267948966
                    },
                    "rotation": 0.0
                  }
                },
                "left": {},
                "rotation": 3.141592653589793
              },
              "rotation": 0.0
            }
          },
          "right": {},
          "left": {},
          "rotation": 1.5707963267948966
        },
        "rotation": 0.0
      }
    },
    "front": {},
    "back": {},
    "spinebrick": true,
    "left": {
      "hinge": {
        "brick": {
          "front": {
            "hinge": {
              "brick": {
                "front": {
                  "hinge": {
                    "brick": {
                      "front": {},
                      "right": {},
                      "left": {},
                      "rotation": -1.5707963267948966
                    },
                    "rotation": -0.0
                  }
                },
                "right": {},
                "left": {
                  "hinge": {
                    "brick": {
                      "front": {},
                      "right": {},
                      "left": {},
                      "rotation": -1.5707963267948966
                    },
                    "rotation": -0.0
                  }
                },
                "rotation": -3.141592653589793
              },
              "rotation": -0.0
            }
          },
          "right": {},
          "left": {},
          "rotation": -1.5707963267948966
        },
        "rotation": -0.0
      }
    }
  },
  "brain_weights_flat": [
    [
      0.0,
      1.3840312710823364,
      0.0,
      0.0,
      0.0,
      0.0,
      0.0,
      0.0,
      -0.2473394427761376,
      0.0,
      0.0,
      0.0,
      0.0,
      0.0,
      0.0,
      0.0
    ],
    [
      2.3499475042326075,
      0.0,
      1.4391145490321993,
      0.45392954154692783,
      0.0,
      0.0,
      0.0,
      0.0,
      0.0,
      0.7101378015280818,
      0.0,
      0.0,
      0.0,
      0.0,
      0.0,
      0.0
    ],
    [
      0.0,
      -2.9138866157917933,
      0.0,
      0.0,
      0.0,
      0.0,
      0.0,
      0.0,
      0.0,
      0.0,
      2.3829048908665413,
      0.0,
      0.0,
      0.0,
      0.0,
      0.0
    ],
    [
      0.0,
      -3.4270575609960345,
      0.0,
      0.0,
      0.0,
      0.0,
      0.0,
      0.0,
      0.0,
      0.0,
      0.0,
      -2.3660292611648233,
      0.0,
      0.0,
      0.0,
      0.0
    ],
    [
      0.0,
      0.0,
      0.0,
      0.0,
      0.0,
      -2.8650114188504348,
      0.0,
      0.0,
      0.0,
      0.0,
      0.0,
      0.0,
      1.234667927758514,
      0.0,
      0.0,
      0.0
    ],
    [
      0.0,
      0.0,
      0.0,
      0.0,
      1.1458120365366444,
      0.0,
      -0.5722253354615874,
      -0.6910579838460651,
      0.0,
      0.0,
      0.0,
      0.0,
      0.0,
      4.037826550173537,
      0.0,
      0.0
    ],
    [
      0.0,
      0.0,
      0.0,
      0.0,
      0.0,
      2.9016416100211693,
      0.0,
      0.0,
      0.0,
      0.0,
      0.0,
      0.0,
      0.0,
      0.0,
      3.3852633055846173,
      0.0
    ],
    [
      0.0,
      0.0,
      0.0,
      0.0,
      0.0,
      0.1300726085454728,
      0.0,
      0.0,
      0.0,
      0.0,
      0.0,
      0.0,
      0.0,
      0.0,
      0.0,
      0.8429126472953428
    ],
    [
      1.2637983130520936,
      0.0,
      0.0,
      0.0,
      0.0,
      0.0,
      0.0,
      0.0,
      0.0,
      0.0,
      0.0,
      0.0,
      0.0,
      0.0,
      0.0,
      0.0
    ],
    [
      0.0,
      -3.177000187094905,
      0.0,
      0.0,
      0.0,
      0.0,
      0.0,
      0.0,
      0.0,
      0.0,
      0.0,
      0.0,
      0.0,
      0.0,
      0.0,
      0.0
    ],
    [
      0.0,
      0.0,
      -1.5686548973458594,
      0.0,
      0.0,
      0.0,
      0.0,
      0.0,
      0.0,
      0.0,
      0.0,
      0.0,
      0.0,
      0.0,
      0.0,
      0.0
    ],
    [
      0.0,
      0.0,
      0.0,
      -3.19634061269295,
      0.0,
      0.0,
      0.0,
      0.0,
      0.0,
      0.0,
      0.0,
      0.0,
      0.0,
      0.0,
      0.0,
      0.0
    ],
    [
      0.0,
      0.0,
      0.0,
      0.0,
      -0.5910819227346338,
      0.0,
      0.0,
      0.0,
      0.0,
      0.0,
      0.0,
      0.0,
      0.0,
      0.0,
      0.0,
      0.0
    ],
    [
      0.0,
      0.0,
      0.0,
      0.0,
      0.0,
      -1.8552574135637585,
      0.0,
      0.0,
      0.0,
      0.0,
      0.0,
      0.0,
      0.0,
      0.0,
      0.0,
      0.0
    ],
    [
      0.0,
      0.0,
      0.0,
      0.0,
      0.0,
      0.0,
      -2.3011442204627532,
      0.0,
      0.0,
      0.0,
      0.0,
      0.0,
      0.0,
      0.0,
      0.0,
      0.0
    ],
    [
      0.0,
      0.0,
      0.0,
      0.0,
      0.0,
      0.0,
      0.0,
      -2.5878426828215852,
      0.0,
      0.0,
      0.0,
      0.0,
      0.0,
      0.0,
      0.0,
      0.0
    ]
  ],
  "brain_weights_uneven": [
    [
      0.0,
      4.619923338305131,
      0.0,
      0.0,
      0.0,
      0.0,
      0.0,
      0.0,
      1.2304952713464339,
      0.0,
      0.0,
      0.0,
      0.0,
      0.0,
      0.0,
      0.0
    ],
    [
      -1.825377275020409,
      0.0,
      2.057097172807538,
      -1.316560499764256,
      0.0,
      0.0,
      0.0,
      0.0,
      0.0,
      0.956928505503897,
      0.0,
      0.0,
      0.0,
      0.0,
      0.0,
      0.0
    ],
    [
      0.0,
      0.7466096852642292,
      0.0,
      0.0,
      0.0,
      0.0,
      0.0,
      0.0,
      0.0,
      0.0,
      -3.1529623479412017,
      0.0,
      0.0,
      0.0,
      0.0,
      0.0
    ],
    [
      0.0,
      1.9134869570408555,
      0.0,
      0.0,
      0.0,
      0.0,
      0.0,
      0.0,
      0.0,
      0.0,
      0.0,
      1.3113770024650033,
      0.0,
      0.0,
      0.0,
      0.0
    ],
    [
      0.0,
      0.0,
      0.0,
      0.0,
      0.0,
      0.031244657499382544,
      0.0,
      0.0,
      0.0,
      0.0,
      0.0,
      0.0,
      2.441828949799065,
      0.0,
      0.0,
      0.0
    ],
    [
      0.0,
      0.0,
      0.0,
      0.0,
      4.599709838757219,
      0.0,
      2.4995866207723862,
      -5.243670264590269,
      0.0,
      0.0,
      0.0,
      0.0,
      0.0,
      1.3224034042173802,
      0.0,
      0.0
    ],
    [
      0.0,
      0.0,
      0.0,
      0.0,
      0.0,
      -3.352338517228138,
      0.0,
      0.0,
      0.0,
      0.0,
      0.0,
      0.0,
      0.0,
      0.0,
      -1.1774639249161014,
      0.0
    ],
    [
      0.0,
      0.0,
      0.0,
      0.0,
      0.0,
      -3.5781711871894872,
      0.0,
      0.0,
      0.0,
      0.0,
      0.0,
      0.0,
      0.0,
      0.0,
      0.0,
      4.518648260250806
    ],
    [
      -3.5900628331325333,
      0.0,
      0.0,
      0.0,
      0.0,
      0.0,
      0.0,
      0.0,
      0.0,
      0.0,
      0.0,
      0.0,
      0.0,
      0.0,
      0.0,
      0.0
    ],
    [
      0.0,
      -1.8155292656536575,
      0.0,
      0.0,
      0.0,
      0.0,
      0.0,
      0.0,
      0.0,
      0.0,
      0.0,
      0.0,
      0.0,
      0.0,
      0.0,
      0.0
    ],
    [
      0.0,
      0.0,
      -1.5941872335209832,
      0.0,
      0.0,
      0.0,
      0.0,
      0.0,
      0.0,
      0.0,
      0.0,
      0.0,
      0.0,
      0.0,
      0.0,
      0.0
    ],
    [
      0.0,
      0.0,
      0.0,
      -0.20962749394831448,
      0.0,
      0.0,
      0.0,
      0.0,
      0.0,
      0.0,
      0.0,
      0.0,
      0.0,
      0.0,
      0.0,
      0.0
    ],
    [
      0.0,
      0.0,
      0.0,
      0.0,
      1.909044232321678,
      0.0,
      0.0,
      0.0,
      0.0,
      0.0,
      0.0,
      0.0,
      0.0,
      0.0,
      0.0,
      0.0
    ],
    [
      0.0,
      0.0,
      0.0,
      0.0,
      0.0,
      -3.1145328187821697,
      0.0,
      0.0,
      0.0,
      0.0,
      0.0,
      0.0,
      0.0,
      0.0,
      0.0,
      0.0
    ],
    [
      0.0,
      0.0,
      0.0,
      0.0,
      0.0,
      0.0,
      2.11078094799668,
      0.0,
      0.0,
      0.0,
      0.0,
      0.0,
      0.0,
      0.0,
      0.0,
      0.0
    ],
    [
      0.0,
      0.0,
      0.0,
      0.0,
      0.0,
      0.0,
      0.0,
      -1.215853143459141,
      0.0,
      0.0,
      0.0,
      0.0,
      0.0,
      0.0,
      0.0,
      0.0
    ]
  ],
  "brain_weights_crater": [
    [
      0.0,
      3.63814440787969,
      0.0,
      0.0,
      0.0,
      0.0,
      0.0,
      0.0,
      5.6821729743604905,
      0.0,
      0.0,
      0.0,
      0.0,
      0.0,
      0.0,
      0.0
    ],
    [
      0.022229252887841278,
      0.0,
      -1.0192769260276986,
      -1.76075169904718,
      0.0,
      0.0,
      0.0,
      0.0,
      0.0,
      0.11088842322541176,
      0.0,
      0.0,
      0.0,
      0.0,
      0.0,
      0.0
    ],
    [
      0.0,
      -1.2088123096708965,
      0.0,
      0.0,
      0.0,
      0.0,
      0.0,
      0.0,
      0.0,
      0.0,
      2.2047318070131676,
      0.0,
      0.0,
      0.0,
      0.0,
      0.0
    ],
    [
      0.0,
      -0.47860348694016464,
      0.0,
      0.0,
      0.0,
      0.0,
      0.0,
      0.0,
      0.0,
      0.0,
      0.0,
      -2.607687320685444,
      0.0,
      0.0,
      0.0,
      0.0
    ],
    [
      0.0,
      0.0,
      0.0,
      0.0,
      0.0,
      0.6536300312705621,
      0.0,
      0.0,
      0.0,
      0.0,
      0.0,
      0.0,
      -0.6679225065984742,
      0.0,
      0.0,
      0.0
    ],
    [
      0.0,
      0.0,
      0.0,
      0.0,
      0.15404153095748196,
      0.0,
      0.9747724523042374,
      0.6918043328488811,
      0.0,
      0.0,
      0.0,
      0.0,
      0.0,
      -2.493840038537432,
      0.0,
      0.0
    ],
    [
      0.0,
      0.0,
      0.0,
      0.0,
      0.0,
      0.7514700431868173,
      0.0,
      0.0,
      0.0,
      0.0,
      0.0,
      0.0,
      0.0,
      0.0,
      5.667476162697934,
      0.0
    ],
    [
      0.0,
      0.0,
      0.0,
      0.0,
      0.0,
      -0.25015176535898176,
      0.0,
      0.0,
      0.0,
      0.0,
      0.0,
      0.0,
      0.0,
      0.0,
      0.0,
      4.1593266395899215
    ],
    [
      -2.9798028285507194,
      0.0,
      0.0,
      0.0,
      0.0,
      0.0,
      0.0,
      0.0,
      0.0,
      0.0,
      0.0,
      0.0,
      0.0,
      0.0,
      0.0,
      0.0
    ],
    [
      0.0,
      3.8330283213878165,
      0.0,
      0.0,
      0.0,
      0.0,
      0.0,
      0.0,
      0.0,
      0.0,
      0.0,
      0.0,
      0.0,
      0.0,
      0.0,
      0.0
    ],
    [
      0.0,
      0.0,
      -3.31155643089644,
      0.0,
      0.0,
      0.0,
      0.0,
      0.0,
      0.0,
      0.0,
      0.0,
      0.0,
      0.0,
      0.0,
      0.0,
      0.0
    ],
    [
      0.0,
      0.0,
      0.0,
      -0.23672976757863567,
      0.0,
      0.0,
      0.0,
      0.0,
      0.0,
      0.0,
      0.0,
      0.0,
      0.0,
      0.0,
      0.0,
      0.0
    ],
    [
      0.0,
      0.0,
      0.0,
      0.0,
      -4.247761773331921,
      0.0,
      0.0,
      0.0,
      0.0,
      0.0,
      0.0,
      0.0,
      0.0,
      0.0,
      0.0,
      0.0
    ],
    [
      0.0,
      0.0,
      0.0,
      0.0,
      0.0,
      3.9130493350209976,
      0.0,
      0.0,
      0.0,
      0.0,
      0.0,
      0.0,
      0.0,
      0.0,
      0.0,
      0.0
    ],
    [
      0.0,
      0.0,
      0.0,
      0.0,
      0.0,
      0.0,
      -0.014478029281682625,
      0.0,
      0.0,
      0.0,
      0.0,
      0.0,
      0.0,
      0.0,
      0.0,
      0.0
    ],
    [
      0.0,
      0.0,
      0.0,
      0.0,
      0.0,
      0.0,
      0.0,
      -0.70050473133236,
      0.0,
      0.0,
      0.0,
      0.0,
      0.0,
      0.0,
      0.0,
      0.0
    ]
  ]
}