{
  "runID": "670013",
  "fitness": 5.973309588619458,
  "generation": 177,
  "core": {
    "right": {
      "hinge": {
        "brick": {
          "front": {
            "hinge": {
              "brick": {
                "front": {
                  "hinge": {
                    "brick": {
                      "front": {},
                      "right": {},
                      "left": {},
                      "rotation": 1.5707963267948966
                    },
                    "rotation": 0.0
                  }
                },
                "right": {},
                "left": {
                  "hinge": {
                    "brick": {
                      "front": {},
                      "right": {},
                      "left": {},
                      "rotation": 0.0
                    },
                    "rotation": 1.5707963267948966
                  }
                },
                "rotation": 4.71238898038469
              },
              "rotation": 3.141592653589793
            }
          },
          "right": {
            "hinge": {
              "brick": {
                "front": {
                  "hinge": {
                    "brick": {
                      "front": {},
                      "right": {},
                      "left": {},
                      "rotation": 3.141592653589793
                    },
                    "rotation": 0.0
                  }
                },
                "right": {},
                "left": {},
                "rotation": 3.141592653589793
              },
              "rotation": 0.0
            }
          },
          "left": {
            "hinge": {
              "brick": {
                "front": {},
                "right": {},
                "left": {},
                "rotation": 0.0
              },
              "rotation": 0.0
            }
          },
          "rotation": 1.5707963267948966
        },
        "rotation": 0.0
      }
    },
    "front": {},
    "back": {},
    "spinebrick": true,
    "left": {
      "hinge": {
        "brick": {
          "front": {
            "hinge": {
              "brick": {
                "front": {
                  "hinge": {
                    "brick": {
                      "front": {},
                      "right": {},
                      "left": {},
                      "rotation": -1.5707963267948966
                    },
                    "rotation": -0.0
                  }
                },
                "right": {
                  "hinge": {
                    "brick": {
                      "front": {},
                      "right": {},
                      "left": {},
                      "rotation": -0.0
                    },
                    "rotation": -1.5707963267948966
                  }
                },
                "left": {},
                "rotation": -4.71238898038469
              },
              "rotation": -3.141592653589793
            }
          },
          "right": {
            "hinge": {
              "brick": {
                "front": {},
                "right": {},
                "left": {},
                "rotation": -0.0
              },
              "rotation": -0.0
            }
          },
          "left": {
            "hinge": {
              "brick": {
                "front": {
                  "hinge": {
                    "brick": {
                      "front": {},
                      "right": {},
                      "left": {},
                      "rotation": -3.141592653589793
                    },
                    "rotation": -0.0
                  }
                },
                "right": {},
                "left": {},
                "rotation": -3.141592653589793
              },
              "rotation": -0.0
            }
          },
          "rotation": -1.5707963267948966
        },
        "rotation": -0.0
      }
    }
  },
  "brain_weights": [
    [
      0.0,
      11.539957810441212,
      0.0,
      0.0,
      0.23737904434516083,
      0.0,
      -0.9018752400778811,
      0.0,
      0.0,
      0.0,
      0.0,
      0.0,
      0.0,
      0.0,
      4.850349790476824,
      0.0,
      0.0,
      0.0,
      0.0,
      0.0,
      0.0,
      0.0,
      0.0,
      0.0,
      0.0,
      0.0,
      0.0,
      0.0
    ],
    [
      -0.7724161776697849,
      0.0,
      5.255319378535618,
      7.704589305972448,
      0.0,
      0.0,
      0.0,
      0.0,
      0.0,
      0.0,
      0.0,
      0.0,
      0.0,
      0.0,
      0.0,
      -3.379411892997883,
      0.0,
      0.0,
      0.0,
      0.0,
      0.0,
      0.0,
      0.0,
      0.0,
      0.0,
      0.0,
      0.0,
      0.0
    ],
    [
      0.0,
      -7.3436414275561415,
      0.0,
      0.0,
      0.0,
      0.0,
      0.0,
      0.0,
      0.0,
      0.0,
      0.0,
      0.0,
      0.0,
      0.0,
      0.0,
      0.0,
      4.546204219143123,
      0.0,
      0.0,
      0.0,
      0.0,
      0.0,
      0.0,
      0.0,
      0.0,
      0.0,
      0.0,
      0.0
    ],
    [
      0.0,
      4.703760996546489,
      0.0,
      0.0,
      0.0,
      0.0,
      0.0,
      0.0,
      0.0,
      0.0,
      0.0,
      0.0,
      0.0,
      0.0,
      0.0,
      0.0,
      0.0,
      6.778569931744308,
      0.0,
      0.0,
      0.0,
      0.0,
      0.0,
      0.0,
      0.0,
      0.0,
      0.0,
      0.0
    ],
    [
      -5.948844043342461,
      0.0,
      0.0,
      0.0,
      0.0,
      2.7228995673024716,
      0.0,
      0.0,
      0.0,
      0.0,
      0.0,
      0.0,
      0.0,
      0.0,
      0.0,
      0.0,
      0.0,
      0.0,
      7.160704169145024,
      0.0,
      0.0,
      0.0,
      0.0,
      0.0,
      0.0,
      0.0,
      0.0,
      0.0
    ],
    [
      0.0,
      0.0,
      0.0,
      0.0,
      -4.3536413240577065,
      0.0,
      0.0,
      0.0,
      0.0,
      0.0,
      0.0,
      0.0,
      0.0,
      0.0,
      0.0,
      0.0,
      0.0,
      0.0,
      0.0,
      0.4286788592755959,
      0.0,
      0.0,
      0.0,
      0.0,
      0.0,
      0.0,
      0.0,
      0.0
    ],
    [
      -2.7496169706916516,
      0.0,
      0.0,
      0.0,
      0.0,
      0.0,
      0.0,
      0.0,
      0.0,
      0.0,
      0.0,
      0.0,
      0.0,
      0.0,
      0.0,
      0.0,
      0.0,
      0.0,
      0.0,
      0.0,
      10.540957041959755,
      0.0,
      0.0,
      0.0,
      0.0,
      0.0,
      0.0,
      0.0
    ],
    [
      0.0,
      0.0,
      0.0,
      0.0,
      0.0,
      0.0,
      0.0,
      0.0,
      2.9677445383949053,
      0.0,
      0.0,
      3.5103285577763597,
      -0.8554987550380221,
      0.0,
      0.0,
      0.0,
      0.0,
      0.0,
      0.0,
      0.0,
      0.0,
      13.008431324843892,
      0.0,
      0.0,
      0.0,
      0.0,
      0.0,
      0.0
    ],
    [
      0.0,
      0.0,
      0.0,
      0.0,
      0.0,
      0.0,
      0.0,
      6.058572444476883,
      0.0,
      0.31179647265753585,
      -3.782147981050338,
      0.0,
      0.0,
      0.0,
      0.0,
      0.0,
      0.0,
      0.0,
      0.0,
      0.0,
      0.0,
      0.0,
      3.159274511353055,
      0.0,
      0.0,
      0.0,
      0.0,
      0.0
    ],
    [
      0.0,
      0.0,
      0.0,
      0.0,
      0.0,
      0.0,
      0.0,
      0.0,
      -1.2898381595419721,
      0.0,
      0.0,
      0.0,
      0.0,
      0.0,
      0.0,
      0.0,
      0.0,
      0.0,
      0.0,
      0.0,
      0.0,
      0.0,
      0.0,
      -8.164850924067805,
      0.0,
      0.0,
      0.0,
      0.0
    ],
    [
      0.0,
      0.0,
      0.0,
      0.0,
      0.0,
      0.0,
      0.0,
      0.0,
      5.738857702059747,
      0.0,
      0.0,
      0.0,
      0.0,
      0.0,
      0.0,
      0.0,
      0.0,
      0.0,
      0.0,
      0.0,
      0.0,
      0.0,
      0.0,
      0.0,
      -0.6296635284764343,
      0.0,
      0.0,
      0.0
    ],
    [
      0.0,
      0.0,
      0.0,
      0.0,
      0.0,
      0.0,
      0.0,
      -1.894722064117726,
      0.0,
      0.0,
      0.0,
      0.0,
      0.0,
      0.0,
      0.0,
      0.0,
      0.0,
      0.0,
      0.0,
      0.0,
      0.0,
      0.0,
      0.0,
      0.0,
      0.0,
      -1.893501708209383,
      0.0,
      0.0
    ],
    [
      0.0,
      0.0,
      0.0,
      0.0,
      0.0,
      0.0,
      0.0,
      -1.4953489064804675,
      0.0,
      0.0,
      0.0,
      0.0,
      0.0,
      -4.679370475195018,
      0.0,
      0.0,
      0.0,
      0.0,
      0.0,
      0.0,
      0.0,
      0.0,
      0.0,
      0.0,
      0.0,
      0.0,
      3.6286575206396585,
      0.0
    ],
    [
      0.0,
      0.0,
      0.0,
      0.0,
      0.0,
      0.0,
      0.0,
      0.0,
      0.0,
      0.0,
      0.0,
      0.0,
      7.310221558298578,
      0.0,
      0.0,
      0.0,
      0.0,
      0.0,
      0.0,
      0.0,
      0.0,
      0.0,
      0.0,
      0.0,
      0.0,
      0.0,
      0.0,
      0.03697576345838205
    ],
    [
      -6.3205570527695425,
      0.0,
      0.0,
      0.0,
      0.0,
      0.0,
      0.0,
      0.0,
      0.0,
      0.0,
      0.0,
      0.0,
      0.0,
      0.0,
      0.0,
      0.0,
      0.0,
      0.0,
      0.0,
      0.0,
      0.0,
      0.0,
      0.0,
      0.0,
      0.0,
      0.0,
      0.0,
      0.0
    ],
    [
      0.0,
      7.382509206736105,
      0.0,
      0.0,
      0.0,
      0.0,
      0.0,
      0.0,
      0.0,
      0.0,
      0.0,
      0.0,
      0.0,
      0.0,
      0.0,
      0.0,
      0.0,
      0.0,
      0.0,
      0.0,
      0.0,
      0.0,
      0.0,
      0.0,
      0.0,
      0.0,
      0.0,
      0.0
    ],
    [
      0.0,
      0.0,
      -3.5672442084519522,
      0.0,
      0.0,
      0.0,
      0.0,
      0.0,
      0.0,
      0.0,
      0.0,
      0.0,
      0.0,
      0.0,
      0.0,
      0.0,
      0.0,
      0.0,
      0.0,
      0.0,
      0.0,
      0.0,
      0.0,
      0.0,
      0.0,
      0.0,
      0.0,
      0.0
    ],
    [
      0.0,
      0.0,
      0.0,
      -3.8480712384982194,
      0.0,
      0.0,
      0.0,
      0.0,
      0.0,
      0.0,
      0.0,
      0.0,
      0.0,
      0.0,
      0.0,
      0.0,
      0.0,
      0.0,
      0.0,
      0.0,
      0.0,
      0.0,
      0.0,
      0.0,
      0.0,
      0.0,
      0.0,
      0.0
    ],
    [
      0.0,
      0.0,
      0.0,
      0.0,
      1.7985005428709353,
      0.0,
      0.0,
      0.0,
      0.0,
      0.0,
      0.0,
      0.0,
      0.0,
      0.0,
      0.0,
      0.0,
      0.0,
      0.0,
      0.0,
      0.0,
      0.0,
      0.0,
      0.0,
      0.0,
      0.0,
      0.0,
      0.0,
      0.0
    ],
    [
      0.0,
      0.0,
      0.0,
      0.0,
      0.0,
      -1.6740537428855526,
      0.0,
      0.0,
      0.0,
      0.0,
      0.0,
      0.0,
      0.0,
      0.0,
      0.0,
      0.0,
      0.0,
      0.0,
      0.0,
      0.0,
      0.0,
      0.0,
      0.0,
      0.0,
      0.0,
      0.0,
      0.0,
      0.0
    ],
    [
      0.0,
      0.0,
      0.0,
      0.0,
      0.0,
      0.0,
      -0.4242698755528882,
      0.0,
      0.0,
      0.0,
      0.0,
      0.0,
      0.0,
      0.0,
      0.0,
      0.0,
      0.0,
      0.0,
      0.0,
      0.0,
      0.0,
      0.0,
      0.0,
      0.0,
      0.0,
      0.0,
      0.0,
      0.0
    ],
    [
      0.0,
      0.0,
      0.0,
      0.0,
      0.0,
      0.0,
      0.0,
      -2.043858652941263,
      0.0,
      0.0,
      0.0,
      0.0,
      0.0,
      0.0,
      0.0,
      0.0,
      0.0,
      0.0,
      0.0,
      0.0,
      0.0,
      0.0,
      0.0,
      0.0,
      0.0,
      0.0,
      0.0,
      0.0
    ],
    [
      0.0,
      0.0,
      0.0,
      0.0,
      0.0,
      0.0,
      0.0,
      0.0,
      -4.571031523031661,
      0.0,
      0.0,
      0.0,
      0.0,
      0.0,
      0.0,
      0.0,
      0.0,
      0.0,
      0.0,
      0.0,
      0.0,
      0.0,
      0.0,
      0.0,
      0.0,
      0.0,
      0.0,
      0.0
    ],
    [
      0.0,
      0.0,
      0.0,
      0.0,
      0.0,
      0.0,
      0.0,
      0.0,
      0.0,
      -1.3967463417961485,
      0.0,
      0.0,
      0.0,
      0.0,
      0.0,
      0.0,
      0.0,
      0.0,
      0.0,
      0.0,
      0.0,
      0.0,
      0.0,
      0.0,
      0.0,
      0.0,
      0.0,
      0.0
    ],
    [
      0.0,
      0.0,
      0.0,
      0.0,
      0.0,
      0.0,
      0.0,
      0.0,
      0.0,
      0.0,
      5.035487708926926,
      0.0,
      0.0,
      0.0,
      0.0,
      0.0,
      0.0,
      0.0,
      0.0,
      0.0,
      0.0,
      0.0,
      0.0,
      0.0,
      0.0,
      0.0,
      0.0,
      0.0
    ],
    [
      0.0,
      0.0,
      0.0,
      0.0,
      0.0,
      0.0,
      0.0,
      0.0,
      0.0,
      0.0,
      0.0,
      3.0641256206898344,
      0.0,
      0.0,
      0.0,
      0.0,
      0.0,
      0.0,
      0.0,
      0.0,
      0.0,
      0.0,
      0.0,
      0.0,
      0.0,
      0.0,
      0.0,
      0.0
    ],
    [
      0.0,
      0.0,
      0.0,
      0.0,
      0.0,
      0.0,
      0.0,
      0.0,
      0.0,
      0.0,
      0.0,
      0.0,
      1.39525002334209,
      0.0,
      0.0,
      0.0,
      0.0,
      0.0,
      0.0,
      0.0,
      0.0,
      0.0,
      0.0,
      0.0,
      0.0,
      0.0,
      0.0,
      0.0
    ],
    [
      0.0,
      0.0,
      0.0,
      0.0,
      0.0,
      0.0,
      0.0,
      0.0,
      0.0,
      0.0,
      0.0,
      0.0,
      0.0,
      4.110871585753247,
      0.0,
      0.0,
      0.0,
      0.0,
      0.0,
      0.0,
      0.0,
      0.0,
      0.0,
      0.0,
      0.0,
      0.0,
      0.0,
      0.0
    ]
  ]
}