{
  "runID": "670023",
  "fitness": 14.54087278519181,
  "generation": 45,
  "core": {
    "right": {
      "hinge": {
        "brick": {
          "front": {
            "hinge": {
              "brick": {
                "front": {},
                "right": {},
                "left": {},
                "rotation": 1.5707963267948966
              },
              "rotation": 4.71238898038469
            }
          },
          "right": {},
          "left": {
            "hinge": {
              "brick": {
                "front": {},
                "right": {},
                "left": {},
                "rotation": 3.141592653589793
              },
              "rotation": 4.71238898038469
            }
          },
          "rotation": 4.71238898038469
        },
        "rotation": 0.0
      }
    },
    "front": {},
    "back": {},
    "spinebrick": true,
    "left": {
      "hinge": {
        "brick": {
          "front": {
            "hinge": {
              "brick": {
                "front": {},
                "right": {},
                "left": {},
                "rotation": -1.5707963267948966
              },
              "rotation": -4.71238898038469
            }
          },
          "right": {
            "hinge": {
              "brick": {
                "front": {},
                "right": {},
                "left": {},
                "rotation": -3.141592653589793
              },
              "rotation": -4.71238898038469
            }
          },
          "left": {},
          "rotation": -4.71238898038469
        },
        "rotation": -0.0
      }
    }
  },
  "brain_weights": [
    [
      0.0,
      -4.664423654635093,
      -12.920298431925417,
      0.0,
      0.0,
      0.0,
      3.1464393228240044,
      0.0,
      0.0,
      0.0,
      0.0,
      0.0
    ],
    [
      -3.0950893391400074,
      0.0,
      0.0,
      0.0,
      0.0,
      0.0,
      0.0,
      11.045152066059918,
      0.0,
      0.0,
      0.0,
      0.0
    ],
    [
      4.890273767145178,
      0.0,
      0.0,
      0.0,
      0.0,
      0.0,
      0.0,
      0.0,
      9.04305007493106,
      0.0,
      0.0,
      0.0
    ],
    [
      0.0,
      0.0,
      0.0,
      0.0,
      7.963382893244817,
      -1.4826945432140084,
      0.0,
      0.0,
      0.0,
      4.860873941969922,
      0.0,
      0.0
    ],
    [
      0.0,
      0.0,
      0.0,
      -10.118321524168893,
      0.0,
      0.0,
      0.0,
      0.0,
      0.0,
      0.0,
      3.8666505287505597,
      0.0
    ],
    [
      0.0,
      0.0,
      0.0,
      -8.109699741201478,
      0.0,
      0.0,
      0.0,
      0.0,
      0.0,
      0.0,
      0.0,
      14.443478988086847
    ],
    [
      6.013013538807162,
      0.0,
      0.0,
      0.0,
      0.0,
      0.0,
      0.0,
      0.0,
      0.0,
      0.0,
      0.0,
      0.0
    ],
    [
      0.0,
      5.502197495989023,
      0.0,
      0.0,
      0.0,
      0.0,
      0.0,
      0.0,
      0.0,
      0.0,
      0.0,
      0.0
    ],
    [
      0.0,
      0.0,
      -10.181545385591923,
      0.0,
      0.0,
      0.0,
      0.0,
      0.0,
      0.0,
      0.0,
      0.0,
      0.0
    ],
    [
      0.0,
      0.0,
      0.0,
      0.5615399493815583,
      0.0,
      0.0,
      0.0,
      0.0,
      0.0,
      0.0,
      0.0,
      0.0
    ],
    [
      0.0,
      0.0,
      0.0,
      0.0,
      -2.0003576964143877,
      0.0,
      0.0,
      0.0,
      0.0,
      0.0,
      0.0,
      0.0
    ],
    [
      0.0,
      0.0,
      0.0,
      0.0,
      0.0,
      -4.519396497127319,
      0.0,
      0.0,
      0.0,
      0.0,
      0.0,
      0.0
    ]
  ]
}